MLclf/MLclf.py
MLclf/__init__.py
MLclf-0.2.14.dist-info/LICENSE
MLclf-0.2.14.dist-info/METADATA
MLclf-0.2.14.dist-info/WHEEL
MLclf-0.2.14.dist-info/top_level.txt
MLclf-0.2.14.dist-info/RECORD
