Metadata-Version: 2.1
Name: MLclf
Version: 0.2.14
Summary: mini-imagenet dataset transformed to fit classification task or keep the format for meta-learning tasks.
Home-page: https://github.com/tiger2017/mlclf
Author: Daniel Cao
Author-email: supercxman@gmail.com
License: MIT
Platform: UNKNOWN
Classifier: Programming Language :: Python :: 3.9
Classifier: Intended Audience :: Science/Research
Classifier: Topic :: Scientific/Engineering
Classifier: Operating System :: OS Independent
Requires-Python: >=3.6
License-File: LICENSE
Requires-Dist: numpy
Requires-Dist: torch
Requires-Dist: torchvision
